<?xml version="1.0" encoding="UTF-8"?>
<i:view xmlns:i="http://www.appflower.com/schema/" xmlns:xsi="http://www.w3.org/2001/XMLSchema-instance" type="layout" xsi:schemaLocation="http://www.appflower.com/schema/appflower.xsd">
    <i:title><![CDATA[dashboard]]></i:title>
    <i:area layout="2" type="content">
        <i:tab title="afCRM">
            <i:component column="0" module="afCrmAccounts" name="listAccounts"/>
            <i:component column="1" module="afCrmContacts" name="listContacts"/>
            <i:component column="1" module="afCrmDeals" name="listDeals"/>
            <i:component column="0" module="afCrmActivity" name="listActivities"/>
            <i:component column="0" module="afCrmStatus" name="listStatuses"/>
        </i:tab>
    </i:area>
	<i:description><![CDATA[Another layout example. This one uses tabs and renders widgets in these. A tab can be split into several columns and may hold any number of widgets. 
	A layout may cotain several tabs. This structure allows the creation of very complex, yet nicely organized views.
	<br><a href="/studio#widget#frontend/pages/dashboard" target="_blank">Open in Studio</a>]]></i:description>
</i:view>
